{"cameraMode":{"drawMode":0,"name":"Shaded","section":"Shading Mode"},"sceneLighting":true,"audioPlay":false,"sceneViewState":{"showFog":true,"showMaterialUpdate":false,"showSkybox":true,"showFlares":true,"showImageEffects":true,"showParticleSystems":true},"in2DMode":false,"pivot":{"x":-20.55779266357422,"y":17.42532730102539,"z":0.007266998291015625},"rotation":{"x":-0.1481580287218094,"y":0.39424583315849306,"z":-0.06452301889657974,"w":-0.9046856760978699},"size":93.17473602294922,"orthographic":false}